Finder138/__init__.py
Finder138-1.2.5.dist-info/LICENSE
Finder138-1.2.5.dist-info/METADATA
Finder138-1.2.5.dist-info/WHEEL
Finder138-1.2.5.dist-info/top_level.txt
Finder138-1.2.5.dist-info/RECORD
