Metadata-Version: 2.1
Name: Finder138
Version: 1.2.5
Summary: iP138数据查询
Home-page: https://github.com/wingram01/Finder138
Author: Andrew Luo
Author-email: luoyanze07@gmail.com
License: UNKNOWN
Keywords: iP138
Platform: UNKNOWN
Classifier: Development Status :: 5 - Production/Stable
Classifier: Intended Audience :: Developers
Classifier: Programming Language :: Python :: 3
Classifier: License :: OSI Approved :: MIT License
Classifier: Natural Language :: Chinese (Simplified)
Classifier: Operating System :: OS Independent
Classifier: Topic :: Internet
Requires-Python: >=3.6
Requires-Dist: requests
